pygtm/__init__.py
pygtm/gtm.py
pygtm/gtm_kaneko.py
pygtm/gtm_mat.py
pygtm-0.0.2.dist-info/METADATA
pygtm-0.0.2.dist-info/RECORD
pygtm-0.0.2.dist-info/WHEEL
pygtm-0.0.2.dist-info/top_level.txt
