Metadata-Version: 2.1
Name: pygtm
Version: 0.0.2
Summary: A python implementation of Generative Topographic Mapping.
Home-page: https://github.com/amaotone/pygtm
Author: Amane Suzuki
Author-email: amane.suzu@gmail.com
License: Copyright (c) 2018 Amane Suzuki
Requires-Dist: numpy
Requires-Dist: scipy
Requires-Dist: scikit-learn
